bsb_family_pack2/__init__.py
bsb_family_pack2/auto_monitor.py
bsb_family_pack2/cli.py
bsb_family_pack2/core.py
bsb_family_pack2/telegram_utils.py
bsb_family_pack2-1.0.0.dist-info/LICENSE
bsb_family_pack2-1.0.0.dist-info/METADATA
bsb_family_pack2-1.0.0.dist-info/WHEEL
bsb_family_pack2-1.0.0.dist-info/entry_points.txt
bsb_family_pack2-1.0.0.dist-info/top_level.txt
bsb_family_pack2-1.0.0.dist-info/RECORD
